MANIFEST.in
README.rst
README.txt
setup.py
tarantool/__init__.py
tarantool/connection.py
tarantool/const.py
tarantool/error.py
tarantool/request.py
tarantool/response.py
tarantool/schema.py
tarantool/space.py
tarantool/utils.py
tarantool_py3.egg-info/PKG-INFO
tarantool_py3.egg-info/SOURCES.txt
tarantool_py3.egg-info/dependency_links.txt
tarantool_py3.egg-info/requires.txt
tarantool_py3.egg-info/top_level.txt