Metadata-Version: 1.1
Name: tarantool-py3
Version: 0.5.1
Summary: Python client library for Tarantool Database
Home-page: https://github.com/tarantool/tarantool-python
Author: Konstantin Cherkasoff
Author-email: k.cherkasoff@gmail.com
License: BSD
Platform: all
Classifier: Intended Audience :: Developers
Classifier: License :: OSI Approved :: BSD License
Classifier: Operating System :: OS Independent
Classifier: Programming Language :: Python
Classifier: Topic :: Database :: Front-Ends
